django_routine/__init__.py
django_routine/start.py
django_routine-0.3.1.dist-info/LICENSE
django_routine-0.3.1.dist-info/METADATA
django_routine-0.3.1.dist-info/WHEEL
django_routine-0.3.1.dist-info/entry_points.txt
django_routine-0.3.1.dist-info/top_level.txt
django_routine-0.3.1.dist-info/RECORD
