Metadata-Version: 2.1
Name: django-routine
Version: 0.3.1
Summary: A Django app for managing routines.
Home-page: https://github.com/DCDie/django-routine
Author: Daniel Cuznetov
Author-email: danielcuznetov04@gmail.com
Project-URL: Bug Tracker, https://github.com/DCDie/django-routine/issues
Classifier: Programming Language :: Python :: 3
Classifier: License :: OSI Approved :: Apache Software License
Classifier: Operating System :: OS Independent
Requires-Python: >=3.9
License-File: LICENSE
Requires-Dist: djangorestframework
Requires-Dist: django
Requires-Dist: django-rest-swagger
Requires-Dist: drf-yasg
Requires-Dist: djangorestframework-simplejwt
Requires-Dist: django-filter
